[


  {
    
    "Quantity": 50,
    "Active": true,
    "ScaledImage":"https://i.etsystatic.com/13074965/r/il/ad6f73/1300707053/il_fullxfull.1300707053_hgsg.jpg",
    "FullImage": "https://i.etsystatic.com/13074965/r/il/ad6f73/1300707053/il_fullxfull.1300707053_hgsg.jpg"
  },
  {
    "Id":2,
    "Name": "Floral jumpsuit",
    "ShortDescription":"Cute jumpsuit with a cute printed design",
    "LongDescription": "Cute jumpsuit with a cute printed design",
    "Catagory": "1",
    "Price": 2500,
    "Quantity": 50,
    "Active": true,
    "ScaledImage": "https://www.forever21.com/images/1_front_750/00382492-01.jpg",
    "FullImage": "https://www.forever21.com/images/1_front_750/00382492-01.jpg"
  },
  {
    "Id":3,
    "Name": "Red sneakers",
    "ShortDescription": "High quality red sneakers",
    "LongDescription": "High quality red sneakers",
    "Catagory": "1",
    "Price": 750,
    "Quantity": 50,
    "Active": true,
    "ScaledImage": "https://www.cmshoes.co.nz/image/cache/data/category_63/8382pro_7-800x800.jpg",
    "FullImage": "https://www.cmshoes.co.nz/image/cache/data/category_63/8382pro_7-800x800.jpg"
  },
  {
    "Id":4,
    "Name": "Strappy black skirt",
    "ShortDescription": "Strappy Black Suspender Skirt Tunic Party Pleated Skater Skirts",
    "LongDescription": "Strappy Black Suspender Skirt Tunic Party Pleated Skater Skirts",
    "Catagory": "1",
    "Price": 100,
    "Quantity": 50,
    "Active": true,
    "ScaledImage": "https://www.channypicture.com/pic/uploadfile2/UploadFile/P0/SKU538951/DB3633C82633995323F1D2738313C8D2995622999DD29ACECA63D253C883CA16999D2313279CCB03C8A053.jpg",
    "FullImage": "https://www.channypicture.com/pic/uploadfile2/UploadFile/P0/SKU538951/DB3633C82633995323F1D2738313C8D2995622999DD29ACECA63D253C883CA16999D2313279CCB03C8A053.jpg"
  },
  {
    "Id":5,
    "Name": "Black long dress",
    "ShortDescription": "Women Long Formal Prom Dress Cocktail Party Gown Evening Bridesmaid Dress Lady.",
    "LongDescription": "Women Long Formal Prom Dress Cocktail Party Gown Evening Bridesmaid Dress Lady.",
    "Catagory": "1",
    "Price": 4800,
    "Quantity": 50,
    "Active": true,
    "ScaledImage": "https://i.ebayimg.com/images/g/ElkAAOSwsYpaMKN~/s-l500.jpg",
    "FullImage": "https://i.ebayimg.com/images/g/ElkAAOSwsYpaMKN~/s-l500.jpg"
  },
  {
    "Id":6,
    "Name": "Blue short dress",
    "ShortDescription": "Womens Summer Casual Off-Shoulder Party Evening Cocktail Swing Short Dress",
    "LongDescription": "Womens Summer Casual Off-Shoulder Party Evening Cocktail Swing Short Dress",
    "Catagory": "1",
    "Price": 3500,
    "Quantity": 50,
    "Active": true,
    "ScaledImage": "https://i.ebayimg.com/images/g/G0MAAOSwB-1Yq-iQ/s-l1600.jpg",
    "FullImage": "https://i.ebayimg.com/images/g/G0MAAOSwB-1Yq-iQ/s-l1600.jpg"
  },
  
  {
      "Id":11,
      "Name": "Polo T-shirt",
      "ShortDescription": "Slim Fit POLO Shirts Summer Solid Short Sleeve Casual T-shirt Work Tee Top ",
      "LongDescription": " Slim Fit POLO Shirts Summer Solid Short Sleeve Casual T-shirt Work Tee Top",
      "Catagory": "2",
      "Price": 2900,
      "Quantity": 50,
      "Active": true,
      "ScaledImage": "https://i.ebayimg.com/images/g/lEkAAOSwNSxVSs3M/s-l500.jpg",
      "FullImage": "https://i.ebayimg.com/images/g/lEkAAOSwNSxVSs3M/s-l500.jpg"
  },
  {
      "Id":12,
      "Name": "Long sleeve shirt T-shirt",
      "ShortDescription": "Slim Fitted Long Sleeve Shirt T-shirt Linen Tee Shirt Casual Top Blouse",
      "LongDescription": "Slim Fitted Long Sleeve Shirt T-shirt Linen Tee Shirt Casual Top Blouse",
      "Catagory": "2",
      "Price": 3300,
      "Quantity": 50,
      "Active": true,
      "ScaledImage": "https://i.ebayimg.com/images/g/L5IAAOSwH05ZunOJ/s-l500.jpg",
      "FullImage": "https://i.ebayimg.com/images/g/L5IAAOSwH05ZunOJ/s-l500.jpg"
  },
  {
      "Id":13,
      "Name": "Denim jeans shirt",
      "ShortDescription": " Men Denim Jeans Shirt Casual Long Sleeve Slim Fit Cotton Tops Shirts HCX ",
      "LongDescription": " Men Denim Jeans Shirt Casual Long Sleeve Slim Fit Cotton Tops Shirts HCX .",
      "Catagory": "2",
      "Price": 2800,
      "Quantity": 50,
      "Active": true,
      "ScaledImage": "https://i.ebayimg.com/images/g/xvoAAOSwhQhY7ef1/s-l1600.jpg",
      "FullImage": "https://i.ebayimg.com/images/g/xvoAAOSwhQhY7ef1/s-l1600.jpg"
  },
  {
      "Id":14,
      "Name": "Long sleeve shirt",
      "ShortDescription": " Slim Fit Long Sleeve Cotton Shirt Plaid Casual Button Business Dress Shirt ",
      "LongDescription": "Slim Fit Long Sleeve Cotton Shirt Plaid Casual Button Business Dress Shirt",
      "Catagory": "2",
      "Price": 21000,
      "Quantity": 50,
      "Active": true,
      "ScaledImage": "https://i.ebayimg.com/images/g/x-YAAOSw5JJZj8Ez/s-l1600.jpg",
      "FullImage": "https://i.ebayimg.com/images/g/x-YAAOSw5JJZj8Ez/s-l1600.jpg"
  },
 
  {
        "Id":15,
        "Name": "Long Sleeve shirt",
        "ShortDescription": "Luxury Fashion Men's Slim Fit Shirt Long Sleeve Dress Shirts Casual Shirt Tops",
        "LongDescription": "Luxury Fashion Men's Slim Fit Shirt Long Sleeve Dress Shirts Casual Shirt Tops",
        "Catagory": "2",
        "Price": 1750,
        "Quantity": 50,
        "Active": true,
        "ScaledImage": "https://i.ebayimg.com/images/g/qEAAAOSw4DJYms0C/s-l1600.jpg",
        "FullImage": "https://i.ebayimg.com/images/g/qEAAAOSw4DJYms0C/s-l1600.jpg"
  },
  {
        "Id":16,
        "Name": "Casual V-Neck shirt",
        "ShortDescription": "Fashion Men's Casual V-Neck Long Sleeve Shirts Slim Fit T-Shirt Tops Blouse Tee",
        "LongDescription": "Fashion Men's Casual V-Neck Long Sleeve Shirts Slim Fit T-Shirt Tops Blouse Tee",
        "Catagory": "2",
        "Price": 2500,
        "Quantity": 50,
        "Active": true,
        "ScaledImage": "https://i.ebayimg.com/images/g/o6MAAOSw4PxZ~~8T/s-l1600.jpg",
        "FullImage": "https://i.ebayimg.com/images/g/o6MAAOSw4PxZ~~8T/s-l1600.jpg"
  },
  {
    "Id": 17,
    "Name": "Girls sweat shirt",
    "ShortDescription": "Girls sweat shirt with rainbow colored stripes",
    "LongDescription": "Girls sweat shirt with rainbow colored stripes",
    "Catagory": "2",
    "Price": 2500,
    "Quantity": 50,
    "Active": true,
    "ScaledImage": "https://assets.jassets.com/h_600,q_95,w_440/v1/assets/images/productimage/2019/2/5/665b6ff4-2521-4ad1-8ac3-478aba3fefb31549362880522-1.jpg",
    "FullImage": "https://assets.jassets.com/h_600,q_95,w_440/v1/assets/images/productimage/2019/2/5/665b6ff4-2521-4ad1-8ac3-478aba3fefb31549362880522-1.jpg"
  }
,
  {
    "Id": 18,
    "Name": "Boys sweat shirt",
    "ShortDescription": "Blue and black color high quality sweatshirt for boys",
    "LongDescription": "Blue and black color high quality sweatshirt for boys",
    "Catagory": "2",
    "Price": 2500,
    "Quantity": 50,
    "Active": true,
    "ScaledImage": "https://www.entre-copines.be/65801-thickbox_default/sweater-here-there-by-ca-secondhand-boys-clothing-for-kids.jpg",
    "FullImage": "https://www.entre-copines.be/65801-thickbox_default/sweater-here-there-by-ca-secondhand-boys-clothing-for-kids.jpg"
  }


]
